{
  "kind": "singleType",
  "collectionName": "tools_boxes",
  "info": {
    "singularName": "tools-box",
    "pluralName": "tools-boxes",
    "displayName": "toolsBox",
    "description": ""
  },
  "options": {
    "draftAndPublish": true
  },
  "pluginOptions": {},
  "attributes": {
    "title": {
      "type": "string",
      "default": "Boite à outils"
    },
    "subtitle": {
      "type": "string",
      "default": "Inclus"
    },
    "description": {
      "type": "text",
      "default": "<p>Au-delà de l’apprentissage obtenez <span style='font-weight: bold; color: black; display: inline-block'>GRATUITEMENT</span> notre boîte à outils complète estimée à $820 canadiens. </p> <p>Bénéficiez d’un accès <span style='font-weight: bold; display: inline-block; color: black'>PREMIUM</span> à <span style='font-weight: bold; display: inline-block; color: black'>CANADIN APP</span> pendant 12 mois. </p> <p>Obtenez le label <span style='font-weight: bold; display: inline-block;color: black '>Canadin Certified.</span></p>"
    },
    "Tools": {
      "type": "component",
      "repeatable": true,
      "component": "tools-box.tools-box"
    }
  }
}
